microjax/__init__.py
microjax/coeffs.py
microjax/likelihood.py
microjax/multipole.py
microjax/point_source.py
microjax/poly_solver.py
microjax/utils.py
microjax/caustics/LICENSE
microjax/caustics/__init__.py
microjax/caustics/integrate.py
microjax/caustics/lightcurve.py
microjax/caustics/extended_source/__init__.py
microjax/caustics/extended_source/contours.py
microjax/caustics/extended_source/limb.py
microjax/caustics/extended_source/mag.py
microjax/caustics/extended_source/segments.py
microjax/fastlens/LICENSE
microjax/fastlens/__init__.py
microjax/fastlens/fftlog.py
microjax/fastlens/fftlog_jax.py
microjax/fastlens/mag_fft.py
microjax/fastlens/mag_fft_jax.py
microjax/fastlens/special.py
microjax/inverse_ray/__init__.py
microjax/inverse_ray/boundary.py
microjax/inverse_ray/cond_extended.py
microjax/inverse_ray/extended_source.py
microjax/inverse_ray/lightcurve.py
microjax/inverse_ray/limb_darkening.py
microjax/inverse_ray/merge_area.py
microjax/trajectory/__init__.py
microjax/trajectory/parallax.py
microjaxx-0.1.1.dist-info/licenses/LICENSE
microjaxx-0.1.1.dist-info/licenses/src/microjax/caustics/LICENSE
microjaxx-0.1.1.dist-info/licenses/src/microjax/fastlens/LICENSE
microjaxx-0.1.1.dist-info/METADATA
microjaxx-0.1.1.dist-info/WHEEL
microjaxx-0.1.1.dist-info/top_level.txt
microjaxx-0.1.1.dist-info/RECORD
