Metadata-Version: 2.4
Name: microjaxx
Version: 0.1.1
Summary: GPU-accelerated, differentiable microlensing modeling in JAX
Author-email: Shota Miyazaki <miyazaki@ir.isas.jaxa.jp>
License-Expression: MIT
Project-URL: Homepage, https://github.com/ShotaMiyazaki94/microjax
Project-URL: Repository, https://github.com/ShotaMiyazaki94/microjax
Project-URL: Issues, https://github.com/ShotaMiyazaki94/microjax/issues
Project-URL: Documentation, https://github.com/ShotaMiyazaki94/microjax#readme
Keywords: jax,microlensing,astronomy,gpu,differentiable
Classifier: Development Status :: 3 - Alpha
Classifier: Intended Audience :: Science/Research
Classifier: Programming Language :: Python
Classifier: Programming Language :: Python :: 3
Classifier: Programming Language :: Python :: 3.9
Classifier: Programming Language :: Python :: 3.10
Classifier: Programming Language :: Python :: 3.11
Classifier: Programming Language :: Python :: 3.12
Classifier: Topic :: Scientific/Engineering :: Astronomy
Classifier: Topic :: Scientific/Engineering :: Mathematics
Classifier: Operating System :: OS Independent
Requires-Python: >=3.9
License-File: LICENSE
License-File: src/microjax/caustics/LICENSE
License-File: src/microjax/fastlens/LICENSE
Requires-Dist: jax>=0.4
Requires-Dist: numpy>=1.26
Provides-Extra: dev
Requires-Dist: pytest; extra == "dev"
Requires-Dist: black; extra == "dev"
Requires-Dist: ruff; extra == "dev"
Requires-Dist: build; extra == "dev"
Requires-Dist: twine; extra == "dev"
Requires-Dist: scipy>=1.10; extra == "dev"
Dynamic: license-file
